biotrade/__init__.py
biotrade/common/__init__.py
biotrade/common/aggregate.py
biotrade/common/compare.py
biotrade/common/country.py
biotrade/common/database.py
biotrade/common/logger.py
biotrade/common/parquet.py
biotrade/common/products.py
biotrade/common/reallocate.py
biotrade/common/sanitize.py
biotrade/common/time_series.py
biotrade/common/update.py
biotrade/common/url_request_header.py
biotrade/comtrade/__init__.py
biotrade/comtrade/aggregate.py
biotrade/comtrade/country_groups.py
biotrade/comtrade/database.py
biotrade/comtrade/dump.py
biotrade/comtrade/products.py
biotrade/comtrade/pump.py
biotrade/comtrade/pump_products.py
biotrade/comtrade/quality.py
biotrade/config_data/column_names.csv
biotrade/config_data/comtrade_commodity_tree.csv
biotrade/config_data/comtrade_faostat_product_mapping.csv
biotrade/config_data/comtrade_hs_2d.csv
biotrade/config_data/comtrade_hs_product_short_names.csv
biotrade/config_data/comtrade_reporters.csv
biotrade/config_data/faostat_commodity_tree.csv
biotrade/config_data/faostat_country_groups.csv
biotrade/config_data/faostat_forestry_production_groups.csv
biotrade/config_data/faostat_forestry_production_short_names.csv
biotrade/config_data/faostat_forestry_trade_groups.csv
biotrade/config_data/faostat_products_name_code_shortname.csv
biotrade/config_data/regulation_products.csv
biotrade/config_data/wood_product_aggregates.csv
biotrade/eurostat/__init__.py
biotrade/eurostat/pump.py
biotrade/faostat/__init__.py
biotrade/faostat/aggregate.py
biotrade/faostat/coefficients.py
biotrade/faostat/convert.py
biotrade/faostat/country.py
biotrade/faostat/country_groups.py
biotrade/faostat/database.py
biotrade/faostat/mirror.py
biotrade/faostat/products.py
biotrade/faostat/pump.py
biotrade/faostat/quality.py
biotrade/faostat/share_coefficients.py
biotrade/hwp/__init__.py
biotrade/hwp/country.py
biotrade/tests/test_aggregate.py
biotrade/tests/test_front_end.py
biotrade/tests/test_mirror.py
biotrade/tests/test_reallocate.py
biotrade-0.4.1.dist-info/licenses/LICENCE.md
biotrade-0.4.1.dist-info/licenses/NOTICE.txt
biotrade-0.4.1.dist-info/METADATA
biotrade-0.4.1.dist-info/WHEEL
biotrade-0.4.1.dist-info/top_level.txt
biotrade-0.4.1.dist-info/RECORD
