Metadata-Version: 2.4
Name: biotrade
Version: 0.4.1
Summary: Agriculture and forestry statistics.
Home-page: https://gitlab.com/bioeconomy/forobs/biotrade/
Author: Paul Rougieux, Selene Patani
Author-email: paul.rougieux@gmail.com
License: MIT
Classifier: Development Status :: 4 - Beta
Classifier: Intended Audience :: Developers
Classifier: License :: OSI Approved :: MIT License
Classifier: Operating System :: OS Independent
Classifier: Programming Language :: Python :: 3.7
Classifier: Programming Language :: Python :: 3.8
Classifier: Programming Language :: Python :: 3.9
Classifier: Topic :: Scientific/Engineering
Requires-Python: >=3.7
License-File: LICENCE.md
License-File: NOTICE.txt
Requires-Dist: pandas
Requires-Dist: sqlalchemy
Requires-Dist: sqlalchemy_utils
Requires-Dist: psycopg2-binary
Requires-Dist: requests
Requires-Dist: scipy
Requires-Dist: pymannkendall
Requires-Dist: matplotlib
Requires-Dist: comtradeapicall
Provides-Extra: api
Requires-Dist: fastapi; extra == "api"
Requires-Dist: uvicorn; extra == "api"
Provides-Extra: arrow
Requires-Dist: pyarrow; extra == "arrow"
Provides-Extra: read
Requires-Dist: dbfread; extra == "read"
Dynamic: author
Dynamic: author-email
Dynamic: classifier
Dynamic: description
Dynamic: description-content-type
Dynamic: home-page
Dynamic: license
Dynamic: license-file
Dynamic: provides-extra
Dynamic: requires-dist
Dynamic: requires-python
Dynamic: summary
